{"seances":[{"id":"s1778835216317","num":1,"date":"2026-05-18","objectif":"essai","obj1":"essai","obj2":"coco","obj3":"plo","autreobj":"","contenus":"","fps":"","bilan":"","aflpTravailles":["Att. 1","Att. 3"],"parties":[],"_done":false},{"id":"s1778835236908","num":2,"date":"2026-05-15","objectif":"top","obj1":"","obj2":"","obj3":"","autreobj":"","contenus":"","fps":"","bilan":"","aflpTravailles":[],"parties":[],"_done":false}],"eleves":[{"id":"e1778835104007io8","nom":"ACHAINTRE Léa","amenagement":"","fiche":null,"noteFinale":null,"trombiPhoto":null},{"id":"e17788351040079bg","nom":"AISSAOUI Adan","amenagement":"","fiche":null,"noteFinale":null,"trombiPhoto":null},{"id":"e1778835104007ajo","nom":"BERKANE Médine","amenagement":"","fiche":null,"noteFinale":null,"trombiPhoto":null},{"id":"e1778835104007qx8","nom":"BICHET Lilou","amenagement":"","fiche":null,"noteFinale":null,"trombiPhoto":null},{"id":"e1778835104007d2z","nom":"BOTTICELLI Fabio","amenagement":"","fiche":null,"noteFinale":null,"trombiPhoto":null},{"id":"e1778835104007l53","nom":"BOURGEON Maxime","amenagement":"","fiche":null,"noteFinale":null,"trombiPhoto":null},{"id":"e1778835104007mr5","nom":"BOUSSEFSAF Lina","amenagement":"","fiche":null,"noteFinale":null,"trombiPhoto":null},{"id":"e177883510400735i","nom":"CASAROTTO Jean","amenagement":"","fiche":null,"noteFinale":null,"trombiPhoto":null},{"id":"e1778835104007h3v","nom":"CAZEAUX Noelie","amenagement":"","fiche":null,"noteFinale":null,"trombiPhoto":null},{"id":"e1778835104007spc","nom":"CHAPUIS Elouan","amenagement":"","fiche":null,"noteFinale":null,"trombiPhoto":null},{"id":"e1778835104007vkr","nom":"CHORFA Zohra","amenagement":"","fiche":null,"noteFinale":null,"trombiPhoto":null},{"id":"e17788351040079pr","nom":"CLAISSE Ophelie","amenagement":"","fiche":null,"noteFinale":null,"trombiPhoto":null},{"id":"e1778835104007ycs","nom":"CROUZET Hugo","amenagement":"","fiche":null,"noteFinale":null,"trombiPhoto":null},{"id":"e1778835104007h1z","nom":"DOMINGUEZ Rafael","amenagement":"","fiche":null,"noteFinale":null,"trombiPhoto":null},{"id":"e1778835104007mz8","nom":"DURANDEU Ambre","amenagement":"","fiche":null,"noteFinale":null,"trombiPhoto":null},{"id":"e1778835104007tci","nom":"GOMBAULD ROSIQUE Maëllysse","amenagement":"","fiche":null,"noteFinale":null,"trombiPhoto":null},{"id":"e1778835104007vs5","nom":"GONCALVES VILELA Lara","amenagement":"","fiche":null,"noteFinale":null,"trombiPhoto":null},{"id":"e1778835104007am0","nom":"JUILLOT Constance","amenagement":"","fiche":null,"noteFinale":null,"trombiPhoto":null},{"id":"e1778835104007myz","nom":"LUMBI Lévi","amenagement":"","fiche":null,"noteFinale":null,"trombiPhoto":null},{"id":"e1778835104007ss0","nom":"MANOHA-ROCHE Tom","amenagement":"","fiche":null,"noteFinale":null,"trombiPhoto":null},{"id":"e17788351040072lh","nom":"MARTINEZ Lyza","amenagement":"","fiche":null,"noteFinale":null,"trombiPhoto":null},{"id":"e1778835104007ehz","nom":"SALMON--MAIRE COME","amenagement":"","fiche":null,"noteFinale":null,"trombiPhoto":null},{"id":"e1778835104007p84","nom":"TOULBI Jasmine","amenagement":"","fiche":null,"noteFinale":null,"trombiPhoto":null},{"id":"e1778835104007ojk","nom":"ZAAFRANE Iyed","amenagement":"","fiche":null,"noteFinale":null,"trombiPhoto":null}],"presences":{"s1778835216317":{"e1778835104007io8":"Present","e17788351040079bg":"Present","e1778835104007ajo":"Present","e1778835104007qx8":"Pas tenue","e1778835104007d2z":"Dispense","e1778835104007l53":"Present","e1778835104007mr5":"Absent","e177883510400735i":"Present","e1778835104007h3v":"Absent","e1778835104007spc":"Present","e1778835104007vkr":"Present","e17788351040079pr":"Present","e1778835104007ycs":"Present","e1778835104007h1z":"Present","e1778835104007mz8":"Present","e1778835104007tci":"Present","e1778835104007vs5":"Present","e1778835104007am0":"Present","e1778835104007myz":"Present","e1778835104007ss0":"Present","e17788351040072lh":"Present","e1778835104007ehz":"Present","e1778835104007p84":"Present","e1778835104007ojk":"Present"}},"autoEval":{"s1778835216317":{}},"seanceObjectifs":{"s1778835216317":{}},"profil":{},"comp":{},"seq":{},"grilleNotes":{},"grille":null,"_meteo":{},"_notes":""}